{
  "cik": "0000006951",
  "ticker": "AMAT",
  "currency": "USD",
  "schema": 3,
  "fiscal_years": [
    2025,
    2024,
    2023,
    2022,
    2021
  ],
  "updated": "2026-06-30T05:02:00Z",
  "source": "SEC EDGAR XBRL companyfacts",
  "statements": {
    "income": [
      {
        "label": "Revenue",
        "unit": "USD",
        "values": {
          "2021": 23063000000,
          "2022": 25785000000,
          "2023": 26517000000,
          "2024": 27176000000,
          "2025": 28368000000
        }
      },
      {
        "label": "Cost of revenue",
        "unit": "USD",
        "values": {
          "2021": 12149000000,
          "2022": 13792000000,
          "2023": 14133000000,
          "2024": 14279000000,
          "2025": 14560000000
        }
      },
      {
        "label": "Gross profit",
        "unit": "USD",
        "values": {
          "2021": 10914000000,
          "2022": 11993000000,
          "2023": 12384000000,
          "2024": 12897000000,
          "2025": 13808000000
        }
      },
      {
        "label": "Operating income",
        "unit": "USD",
        "values": {
          "2021": 6889000000,
          "2022": 7788000000,
          "2023": 7654000000,
          "2024": 7867000000,
          "2025": 8289000000
        }
      },
      {
        "label": "R&D expense",
        "unit": "USD",
        "values": {
          "2021": 2485000000,
          "2022": 2771000000,
          "2023": 3102000000,
          "2024": 3233000000,
          "2025": 3570000000
        }
      },
      {
        "label": "Net income",
        "unit": "USD",
        "values": {
          "2021": 5888000000,
          "2022": 6525000000,
          "2023": 6856000000,
          "2024": 7177000000,
          "2025": 6998000000
        }
      },
      {
        "label": "Diluted EPS",
        "unit": "USD/shares",
        "values": {
          "2021": 6.4,
          "2022": 7.44,
          "2023": 8.11,
          "2024": 8.61,
          "2025": 8.66
        }
      }
    ],
    "balance": [
      {
        "label": "Total assets",
        "unit": "USD",
        "values": {
          "2021": 25825000000,
          "2022": 26726000000,
          "2023": 30729000000,
          "2024": 34409000000,
          "2025": 36299000000
        }
      },
      {
        "label": "Current assets",
        "unit": "USD",
        "values": {
          "2021": 16107000000,
          "2022": 15925000000,
          "2023": 19147000000,
          "2024": 21220000000,
          "2025": 20881000000
        }
      },
      {
        "label": "Total liabilities",
        "unit": "USD",
        "values": {
          "2021": 13578000000,
          "2022": 14532000000,
          "2023": 14380000000,
          "2024": 15408000000,
          "2025": 15884000000
        }
      },
      {
        "label": "Current liabilities",
        "unit": "USD",
        "values": {
          "2021": 6344000000,
          "2022": 7379000000,
          "2023": 7372000000,
          "2024": 8468000000,
          "2025": 7999000000
        }
      },
      {
        "label": "Stockholders' equity",
        "unit": "USD",
        "values": {
          "2021": 12247000000,
          "2022": 12194000000,
          "2023": 16349000000,
          "2024": 19001000000,
          "2025": 20415000000
        }
      },
      {
        "label": "Cash & equivalents",
        "unit": "USD",
        "values": {
          "2021": 4995000000,
          "2022": 1995000000,
          "2023": 6132000000,
          "2024": 8022000000,
          "2025": 7241000000
        }
      }
    ],
    "cashflow": [
      {
        "label": "Operating cash flow",
        "unit": "USD",
        "values": {
          "2021": 5442000000,
          "2022": 5399000000,
          "2023": 8700000000,
          "2024": 8677000000,
          "2025": 7958000000
        }
      },
      {
        "label": "Investing cash flow",
        "unit": "USD",
        "values": {
          "2021": -1216000000,
          "2022": -1357000000,
          "2023": -1535000000,
          "2024": -2327000000,
          "2025": -2782000000
        }
      },
      {
        "label": "Financing cash flow",
        "unit": "USD",
        "values": {
          "2021": -4591000000,
          "2022": -7043000000,
          "2023": -3032000000,
          "2024": -4470000000,
          "2025": -5977000000
        }
      },
      {
        "label": "Capital expenditure",
        "unit": "USD",
        "values": {
          "2021": 668000000,
          "2022": 787000000,
          "2023": 1106000000,
          "2024": 1190000000,
          "2025": 2260000000
        }
      }
    ]
  },
  "based_on_accession": "0001628280-26-037227"
}